{"last_updated": 1556663429, "ttl": 60, "data": {"bikes": [{"bike_id": "bike_25905", "name": "1369", "lon": -71.412995, "lat": 41.81948333333333, "is_reserved": 0, "is_disabled": 0, "jump_ebike_battery_level": "75%", "jump_vehicle_type": "bike"}, {"bike_id": "bike_25585", "name": "3766", "lon": -71.43500333333333, "lat": 41.82758833333333, "is_reserved": 0, "is_disabled": 0, "jump_ebike_battery_level": "80%", "jump_vehicle_type": "bike"}, {"bike_id": "bike_25991", "name": "1620", "lon": -71.39601, "lat": 41.854076666666664, "is_reserved": 0, "is_disabled": 0, "jump_ebike_battery_level": "69%", "jump_vehicle_type": "bike"}, {"bike_id": "bike_25733", "name": "3630", "lon": -71.44070833333333, "lat": 41.82394333333333, "is_reserved": 0, "is_disabled": 0, "jump_ebike_battery_level": "71%", "jump_vehicle_type": "bike"}, {"bike_id": "bike_25671", "name": "4881", "lon": -71.42361333333334, "lat": 41.821745, "is_reserved": 0, "is_disabled": 0, "jump_ebike_battery_level": "72%", "jump_vehicle_type": "bike"}, {"bike_id": "bike_25854", "name": "0872", "lon": -71.43087666666666, "lat": 41.807965, "is_reserved": 0, "is_disabled": 0, "jump_ebike_battery_level": "74%", "jump_vehicle_type": "bike"}, {"bike_id": "bike_25896", "name": "1335", "lon": -71.40883166666667, "lat": 41.83156, "is_reserved": 0, "is_disabled": 0, "jump_ebike_battery_level": "70%", "jump_vehicle_type": "bike"}, {"bike_id": "bike_25755", "name": "3652", "lon": -71.38289, "lat": 41.82973333333333, "is_reserved": 0, "is_disabled": 0, "jump_ebike_battery_level": "41%", "jump_vehicle_type": "bike"}, {"bike_id": "bike_26036", "name": "4902", "lon": -71.40601, "lat": 41.82344833333333, "is_reserved": 0, "is_disabled": 0, "jump_ebike_battery_level": "63%", "jump_vehicle_type": "bike"}, {"bike_id": "bike_25866", "name": "1078", "lon": -71.40926333333333, "lat": 41.803935, "is_reserved": 0, "is_disabled": 0, "jump_ebike_battery_level": "59%", "jump_vehicle_type": "bike"}, {"bike_id": "bike_26050", "name": "4916", "lon": -71.413215, "lat": 41.844008333333335, "is_reserved": 0, "is_disabled": 0, "jump_ebike_battery_level": "43%", "jump_vehicle_type": "bike"}, {"bike_id": "bike_25883", "name": "1271", "lon": -71.39448666666667, "lat": 41.842866666666666, "is_reserved": 0, "is_disabled": 0, "jump_ebike_battery_level": "61%", "jump_vehicle_type": "bike"}, {"bike_id": "bike_25954", "name": "1640", "lon": -71.390485, "lat": 41.81736166666666, "is_reserved": 0, "is_disabled": 0, "jump_ebike_battery_level": "70%", "jump_vehicle_type": "bike"}, {"bike_id": "bike_26024", "name": "4890", "lon": -71.40908333333333, "lat": 41.824315, "is_reserved": 0, "is_disabled": 0, "jump_ebike_battery_level": "67%", "jump_vehicle_type": "bike"}, {"bike_id": "bike_25869", "name": "1107", "lon": -71.41320833333333, "lat": 41.8188, "is_reserved": 0, "is_disabled": 0, "jump_ebike_battery_level": "52%", "jump_vehicle_type": "bike"}, {"bike_id": "bike_25618", "name": "3799", "lon": -71.41564333333334, "lat": 41.82438166666667, "is_reserved": 0, "is_disabled": 0, "jump_ebike_battery_level": "43%", "jump_vehicle_type": "bike"}, {"bike_id": "bike_25666", "name": "4876", "lon": -71.38921, "lat": 41.81886, "is_reserved": 0, "is_disabled": 0, "jump_ebike_battery_level": "46%", "jump_vehicle_type": "bike"}, {"bike_id": "bike_25634", "name": "3815", "lon": -71.40741166666666, "lat": 41.83931833333333, "is_reserved": 0, "is_disabled": 0, "jump_ebike_battery_level": "64%", "jump_vehicle_type": "bike"}, {"bike_id": "bike_26051", "name": "4917", "lon": -71.45262166666667, "lat": 41.81652, "is_reserved": 0, "is_disabled": 0, "jump_ebike_battery_level": "59%", "jump_vehicle_type": "bike"}, {"bike_id": "bike_26025", "name": "4891", "lon": -71.40197333333333, "lat": 41.818448333333336, "is_reserved": 0, "is_disabled": 0, "jump_ebike_battery_level": "49%", "jump_vehicle_type": "bike"}, {"bike_id": "bike_25965", "name": "1615", "lon": -71.42570333333333, "lat": 41.81975166666667, "is_reserved": 0, "is_disabled": 0, "jump_ebike_battery_level": "37%", "jump_vehicle_type": "bike"}, {"bike_id": "bike_25959", "name": "1599", "lon": -71.40846666666667, "lat": 41.83672166666667, "is_reserved": 0, "is_disabled": 0, "jump_ebike_battery_level": "78%", "jump_vehicle_type": "bike"}, {"bike_id": "bike_25592", "name": "3773", "lon": -71.40804, "lat": 41.80768833333333, "is_reserved": 0, "is_disabled": 0, "jump_ebike_battery_level": "55%", "jump_vehicle_type": "bike"}, {"bike_id": "bike_25924", "name": "1493", "lon": -71.41266666666667, "lat": 41.82931333333333, "is_reserved": 0, "is_disabled": 0, "jump_ebike_battery_level": "42%", "jump_vehicle_type": "bike"}, {"bike_id": "bike_26048", "name": "4914", "lon": -71.39435666666667, "lat": 41.82753833333334, "is_reserved": 0, "is_disabled": 0, "jump_ebike_battery_level": "85%", "jump_vehicle_type": "bike"}, {"bike_id": "bike_25616", "name": "3797", "lon": -71.450285, "lat": 41.82944333333333, "is_reserved": 0, "is_disabled": 0, "jump_ebike_battery_level": "40%", "jump_vehicle_type": "bike"}, {"bike_id": "bike_25768", "name": "3665", "lon": -71.38765833333333, "lat": 41.83405333333333, "is_reserved": 0, "is_disabled": 0, "jump_ebike_battery_level": "62%", "jump_vehicle_type": "bike"}, {"bike_id": "bike_25875", "name": "1166", "lon": -71.436755, "lat": 41.82553166666667, "is_reserved": 0, "is_disabled": 0, "jump_ebike_battery_level": "38%", "jump_vehicle_type": "bike"}, {"bike_id": "bike_25853", "name": "0852", "lon": -71.38859, "lat": 41.828846666666664, "is_reserved": 0, "is_disabled": 0, "jump_ebike_battery_level": "48%", "jump_vehicle_type": "bike"}, {"bike_id": "bike_25563", "name": "3744", "lon": -71.40561333333333, "lat": 41.822875, "is_reserved": 0, "is_disabled": 0, "jump_ebike_battery_level": "75%", "jump_vehicle_type": "bike"}, {"bike_id": "bike_25778", "name": "3675", "lon": -71.41322, "lat": 41.818755, "is_reserved": 0, "is_disabled": 0, "jump_ebike_battery_level": "85%", "jump_vehicle_type": "bike"}, {"bike_id": "bike_25813", "name": "3710", "lon": -71.43504166666666, "lat": 41.827508333333334, "is_reserved": 0, "is_disabled": 0, "jump_ebike_battery_level": "71%", "jump_vehicle_type": "bike"}, {"bike_id": "bike_25825", "name": "3722", "lon": -71.41907666666667, "lat": 41.81651333333333, "is_reserved": 0, "is_disabled": 0, "jump_ebike_battery_level": "41%", "jump_vehicle_type": "bike"}, {"bike_id": "bike_25940", "name": "1546", "lon": -71.40054166666667, "lat": 41.81945833333333, "is_reserved": 0, "is_disabled": 0, "jump_ebike_battery_level": "43%", "jump_vehicle_type": "bike"}, {"bike_id": "bike_25844", "name": "3741", "lon": -71.43058166666667, "lat": 41.840716666666665, "is_reserved": 0, "is_disabled": 0, "jump_ebike_battery_level": "71%", "jump_vehicle_type": "bike"}, {"bike_id": "bike_25562", "name": "3743", "lon": -71.416015, "lat": 41.823275, "is_reserved": 0, "is_disabled": 0, "jump_ebike_battery_level": "48%", "jump_vehicle_type": "bike"}, {"bike_id": "bike_26049", "name": "4915", "lon": -71.39781333333333, "lat": 41.83692833333333, "is_reserved": 0, "is_disabled": 0, "jump_ebike_battery_level": "47%", "jump_vehicle_type": "bike"}, {"bike_id": "bike_25565", "name": "3746", "lon": -71.41513833333333, "lat": 41.811341666666664, "is_reserved": 0, "is_disabled": 0, "jump_ebike_battery_level": "60%", "jump_vehicle_type": "bike"}, {"bike_id": "bike_25578", "name": "3759", "lon": -71.390455, "lat": 41.817418333333336, "is_reserved": 0, "is_disabled": 0, "jump_ebike_battery_level": "52%", "jump_vehicle_type": "bike"}, {"bike_id": "bike_25880", "name": "1242", "lon": -71.42772833333333, "lat": 41.81972666666667, "is_reserved": 0, "is_disabled": 0, "jump_ebike_battery_level": "69%", "jump_vehicle_type": "bike"}, {"bike_id": "bike_26032", "name": "4898", "lon": -71.397955, "lat": 41.83038166666667, "is_reserved": 0, "is_disabled": 0, "jump_ebike_battery_level": "60%", "jump_vehicle_type": "bike"}, {"bike_id": "bike_25777", "name": "3674", "lon": -71.40968166666667, "lat": 41.820528333333336, "is_reserved": 0, "is_disabled": 0, "jump_ebike_battery_level": "60%", "jump_vehicle_type": "bike"}, {"bike_id": "bike_25665", "name": "4875", "lon": -71.40573666666667, "lat": 41.79098333333334, "is_reserved": 0, "is_disabled": 0, "jump_ebike_battery_level": "46%", "jump_vehicle_type": "bike"}, {"bike_id": "bike_25674", "name": "4884", "lon": -71.46703666666667, "lat": 41.83386333333333, "is_reserved": 0, "is_disabled": 0, "jump_ebike_battery_level": "69%", "jump_vehicle_type": "bike"}, {"bike_id": "bike_25809", "name": "3706", "lon": -71.41006166666666, "lat": 41.835971666666666, "is_reserved": 0, "is_disabled": 0, "jump_ebike_battery_level": "71%", "jump_vehicle_type": "bike"}, {"bike_id": "bike_25899", "name": "1345", "lon": -71.38509, "lat": 41.83649166666667, "is_reserved": 0, "is_disabled": 0, "jump_ebike_battery_level": "64%", "jump_vehicle_type": "bike"}, {"bike_id": "bike_25817", "name": "3714", "lon": -71.38221166666666, "lat": 41.82683333333333, "is_reserved": 0, "is_disabled": 0, "jump_ebike_battery_level": "75%", "jump_vehicle_type": "bike"}, {"bike_id": "bike_26054", "name": "4920", "lon": -71.38875666666667, "lat": 41.828601666666664, "is_reserved": 0, "is_disabled": 0, "jump_ebike_battery_level": "68%", "jump_vehicle_type": "bike"}, {"bike_id": "bike_25852", "name": "845", "lon": -71.39028666666667, "lat": 41.81882, "is_reserved": 0, "is_disabled": 0, "jump_ebike_battery_level": "91%", "jump_vehicle_type": "bike"}, {"bike_id": "bike_25597", "name": "3778", "lon": -71.40248166666667, "lat": 41.83027333333333, "is_reserved": 0, "is_disabled": 0, "jump_ebike_battery_level": "75%", "jump_vehicle_type": "bike"}, {"bike_id": "bike_25642", "name": "4852", "lon": -71.405655, "lat": 41.826385, "is_reserved": 0, "is_disabled": 0, "jump_ebike_battery_level": "47%", "jump_vehicle_type": "bike"}, {"bike_id": "bike_25961", "name": "1609", "lon": -71.41157166666666, "lat": 41.82850666666667, "is_reserved": 0, "is_disabled": 0, "jump_ebike_battery_level": "63%", "jump_vehicle_type": "bike"}, {"bike_id": "bike_25787", "name": "3684", "lon": -71.40536333333333, "lat": 41.82255333333333, "is_reserved": 0, "is_disabled": 0, "jump_ebike_battery_level": "69%", "jump_vehicle_type": "bike"}, {"bike_id": "bike_25731", "name": "3628", "lon": -71.40127666666666, "lat": 41.82538, "is_reserved": 0, "is_disabled": 0, "jump_ebike_battery_level": "63%", "jump_vehicle_type": "bike"}, {"bike_id": "bike_25821", "name": "3718", "lon": -71.40589833333334, "lat": 41.84502666666667, "is_reserved": 0, "is_disabled": 0, "jump_ebike_battery_level": "68%", "jump_vehicle_type": "bike"}, {"bike_id": "bike_25619", "name": "3800", "lon": -71.40292666666667, "lat": 41.831451666666666, "is_reserved": 0, "is_disabled": 0, "jump_ebike_battery_level": "62%", "jump_vehicle_type": "bike"}, {"bike_id": "bike_26063", "name": "4929", "lon": -71.39794, "lat": 41.830365, "is_reserved": 0, "is_disabled": 0, "jump_ebike_battery_level": "70%", "jump_vehicle_type": "bike"}, {"bike_id": "bike_26072", "name": "4938", "lon": -71.39263166666667, "lat": 41.834891666666664, "is_reserved": 0, "is_disabled": 0, "jump_ebike_battery_level": "78%", "jump_vehicle_type": "bike"}, {"bike_id": "bike_25774", "name": "3671", "lon": -71.42798333333333, "lat": 41.820116666666664, "is_reserved": 0, "is_disabled": 0, "jump_ebike_battery_level": "72%", "jump_vehicle_type": "bike"}, {"bike_id": "bike_25626", "name": "3807", "lon": -71.41527166666667, "lat": 41.826591666666666, "is_reserved": 0, "is_disabled": 0, "jump_ebike_battery_level": "70%", "jump_vehicle_type": "bike"}, {"bike_id": "bike_25675", "name": "4885", "lon": -71.432165, "lat": 41.81910833333333, "is_reserved": 0, "is_disabled": 0, "jump_ebike_battery_level": "46%", "jump_vehicle_type": "bike"}, {"bike_id": "bike_25573", "name": "3754", "lon": -71.40467666666666, "lat": 41.825655, "is_reserved": 0, "is_disabled": 0, "jump_ebike_battery_level": "41%", "jump_vehicle_type": "bike"}, {"bike_id": "bike_25657", "name": "4867", "lon": -71.40474, "lat": 41.84728333333334, "is_reserved": 0, "is_disabled": 0, "jump_ebike_battery_level": "53%", "jump_vehicle_type": "bike"}, {"bike_id": "bike_26062", "name": "4928", "lon": -71.43104, "lat": 41.85191, "is_reserved": 0, "is_disabled": 0, "jump_ebike_battery_level": "59%", "jump_vehicle_type": "bike"}, {"bike_id": "bike_26061", "name": "4927", "lon": -71.43620833333334, "lat": 41.822896666666665, "is_reserved": 0, "is_disabled": 0, "jump_ebike_battery_level": "68%", "jump_vehicle_type": "bike"}, {"bike_id": "bike_26038", "name": "4904", "lon": -71.39367166666666, "lat": 41.83013166666667, "is_reserved": 0, "is_disabled": 0, "jump_ebike_battery_level": "74%", "jump_vehicle_type": "bike"}, {"bike_id": "bike_25593", "name": "3774", "lon": -71.42308833333334, "lat": 41.822145, "is_reserved": 0, "is_disabled": 0, "jump_ebike_battery_level": "58%", "jump_vehicle_type": "bike"}, {"bike_id": "bike_26069", "name": "4935", "lon": -71.38618666666666, "lat": 41.825736666666664, "is_reserved": 0, "is_disabled": 0, "jump_ebike_battery_level": "49%", "jump_vehicle_type": "bike"}, {"bike_id": "bike_26022", "name": "4888", "lon": -71.38688166666667, "lat": 41.82574833333334, "is_reserved": 0, "is_disabled": 0, "jump_ebike_battery_level": "45%", "jump_vehicle_type": "bike"}, {"bike_id": "bike_25769", "name": "3666", "lon": -71.40393, "lat": 41.792555, "is_reserved": 0, "is_disabled": 0, "jump_ebike_battery_level": "42%", "jump_vehicle_type": "bike"}, {"bike_id": "bike_25744", "name": "3641", "lon": -71.39684333333334, "lat": 41.82329166666667, "is_reserved": 0, "is_disabled": 0, "jump_ebike_battery_level": "42%", "jump_vehicle_type": "bike"}, {"bike_id": "bike_25935", "name": "1522", "lon": -71.43155, "lat": 41.821441666666665, "is_reserved": 0, "is_disabled": 0, "jump_ebike_battery_level": "63%", "jump_vehicle_type": "bike"}, {"bike_id": "bike_25843", "name": "3740", "lon": -71.401685, "lat": 41.833, "is_reserved": 0, "is_disabled": 0, "jump_ebike_battery_level": "58%", "jump_vehicle_type": "bike"}, {"bike_id": "bike_25748", "name": "3645", "lon": -71.41573833333334, "lat": 41.832615, "is_reserved": 0, "is_disabled": 0, "jump_ebike_battery_level": "73%", "jump_vehicle_type": "bike"}, {"bike_id": "bike_25651", "name": "4861", "lon": -71.42885833333334, "lat": 41.822851666666665, "is_reserved": 0, "is_disabled": 0, "jump_ebike_battery_level": "67%", "jump_vehicle_type": "bike"}, {"bike_id": "bike_25569", "name": "3750", "lon": -71.42009166666666, "lat": 41.833981666666666, "is_reserved": 0, "is_disabled": 0, "jump_ebike_battery_level": "70%", "jump_vehicle_type": "bike"}, {"bike_id": "bike_25643", "name": "4853", "lon": -71.40849666666666, "lat": 41.826863333333336, "is_reserved": 0, "is_disabled": 0, "jump_ebike_battery_level": "57%", "jump_vehicle_type": "bike"}, {"bike_id": "bike_26030", "name": "4896", "lon": -71.40857, "lat": 41.818661666666664, "is_reserved": 0, "is_disabled": 0, "jump_ebike_battery_level": "70%", "jump_vehicle_type": "bike"}, {"bike_id": "bike_25625", "name": "3806", "lon": -71.38909166666667, "lat": 41.818865, "is_reserved": 0, "is_disabled": 0, "jump_ebike_battery_level": "40%", "jump_vehicle_type": "bike"}, {"bike_id": "bike_26059", "name": "4925", "lon": -71.41183333333333, "lat": 41.82172166666667, "is_reserved": 0, "is_disabled": 0, "jump_ebike_battery_level": "48%", "jump_vehicle_type": "bike"}, {"bike_id": "bike_25614", "name": "3795", "lon": -71.408665, "lat": 41.8299, "is_reserved": 0, "is_disabled": 0, "jump_ebike_battery_level": "40%", "jump_vehicle_type": "bike"}, {"bike_id": "bike_25572", "name": "3753", "lon": -71.39744166666667, "lat": 41.81893, "is_reserved": 0, "is_disabled": 0, "jump_ebike_battery_level": "75%", "jump_vehicle_type": "bike"}, {"bike_id": "bike_25912", "name": "1405", "lon": -71.39339666666666, "lat": 41.84211666666667, "is_reserved": 0, "is_disabled": 0, "jump_ebike_battery_level": "49%", "jump_vehicle_type": "bike"}, {"bike_id": "bike_25780", "name": "3677", "lon": -71.43949666666667, "lat": 41.80891333333334, "is_reserved": 0, "is_disabled": 0, "jump_ebike_battery_level": "57%", "jump_vehicle_type": "bike"}, {"bike_id": "bike_25668", "name": "4878", "lon": -71.396515, "lat": 41.850775, "is_reserved": 0, "is_disabled": 0, "jump_ebike_battery_level": "70%", "jump_vehicle_type": "bike"}, {"bike_id": "bike_26034", "name": "4900", "lon": -71.40558333333334, "lat": 41.82642166666667, "is_reserved": 0, "is_disabled": 0, "jump_ebike_battery_level": "41%", "jump_vehicle_type": "bike"}, {"bike_id": "bike_25770", "name": "3667", "lon": -71.391105, "lat": 41.85809166666667, "is_reserved": 0, "is_disabled": 0, "jump_ebike_battery_level": "58%", "jump_vehicle_type": "bike"}, {"bike_id": "bike_25962", "name": "1610", "lon": -71.38214666666667, "lat": 41.82711166666667, "is_reserved": 0, "is_disabled": 0, "jump_ebike_battery_level": "62%", "jump_vehicle_type": "bike"}, {"bike_id": "bike_25820", "name": "3717", "lon": -71.42143666666666, "lat": 41.809643333333334, "is_reserved": 0, "is_disabled": 0, "jump_ebike_battery_level": "52%", "jump_vehicle_type": "bike"}, {"bike_id": "bike_25841", "name": "3738", "lon": -71.38753833333334, "lat": 41.834095, "is_reserved": 0, "is_disabled": 0, "jump_ebike_battery_level": "68%", "jump_vehicle_type": "bike"}, {"bike_id": "bike_26037", "name": "4903", "lon": -71.40139833333333, "lat": 41.82792833333333, "is_reserved": 0, "is_disabled": 0, "jump_ebike_battery_level": "57%", "jump_vehicle_type": "bike"}, {"bike_id": "bike_25658", "name": "4868", "lon": -71.38997166666667, "lat": 41.830799999999996, "is_reserved": 0, "is_disabled": 0, "jump_ebike_battery_level": "53%", "jump_vehicle_type": "bike"}, {"bike_id": "bike_26052", "name": "4918", "lon": -71.41157333333334, "lat": 41.816896666666665, "is_reserved": 0, "is_disabled": 0, "jump_ebike_battery_level": "82%", "jump_vehicle_type": "bike"}, {"bike_id": "bike_25840", "name": "3737", "lon": -71.40755666666666, "lat": 41.80757666666667, "is_reserved": 0, "is_disabled": 0, "jump_ebike_battery_level": "43%", "jump_vehicle_type": "bike"}, {"bike_id": "bike_25637", "name": "3818", "lon": -71.39685, "lat": 41.83072666666666, "is_reserved": 0, "is_disabled": 0, "jump_ebike_battery_level": "49%", "jump_vehicle_type": "bike"}, {"bike_id": "bike_25771", "name": "3668", "lon": -71.41382166666666, "lat": 41.825446666666664, "is_reserved": 0, "is_disabled": 0, "jump_ebike_battery_level": "62%", "jump_vehicle_type": "bike"}, {"bike_id": "bike_25865", "name": "1056", "lon": -71.39946666666667, "lat": 41.83007666666666, "is_reserved": 0, "is_disabled": 0, "jump_ebike_battery_level": "86%", "jump_vehicle_type": "bike"}, {"bike_id": "bike_25786", "name": "3683", "lon": -71.401635, "lat": 41.830088333333336, "is_reserved": 0, "is_disabled": 0, "jump_ebike_battery_level": "53%", "jump_vehicle_type": "bike"}, {"bike_id": "bike_25632", "name": "3813", "lon": -71.446115, "lat": 41.823283333333336, "is_reserved": 0, "is_disabled": 0, "jump_ebike_battery_level": "49%", "jump_vehicle_type": "bike"}, {"bike_id": "bike_25577", "name": "3758", "lon": -71.43390833333333, "lat": 41.805323333333334, "is_reserved": 0, "is_disabled": 0, "jump_ebike_battery_level": "51%", "jump_vehicle_type": "bike"}, {"bike_id": "bike_25934", "name": "1521", "lon": -71.42377333333333, "lat": 41.823325, "is_reserved": 0, "is_disabled": 0, "jump_ebike_battery_level": "51%", "jump_vehicle_type": "bike"}, {"bike_id": "bike_25904", "name": "1357", "lon": -71.38554, "lat": 41.834875, "is_reserved": 0, "is_disabled": 0, "jump_ebike_battery_level": "87%", "jump_vehicle_type": "bike"}, {"bike_id": "bike_25765", "name": "3662", "lon": -71.414175, "lat": 41.79278333333333, "is_reserved": 0, "is_disabled": 0, "jump_ebike_battery_level": "46%", "jump_vehicle_type": "bike"}, {"bike_id": "bike_25794", "name": "3691", "lon": -71.41247333333334, "lat": 41.84585833333333, "is_reserved": 0, "is_disabled": 0, "jump_ebike_battery_level": "36%", "jump_vehicle_type": "bike"}, {"bike_id": "bike_25783", "name": "3680", "lon": -71.41411, "lat": 41.82180666666667, "is_reserved": 0, "is_disabled": 0, "jump_ebike_battery_level": "89%", "jump_vehicle_type": "bike"}, {"bike_id": "bike_25591", "name": "3772", "lon": -71.42765333333334, "lat": 41.82077833333334, "is_reserved": 0, "is_disabled": 0, "jump_ebike_battery_level": "54%", "jump_vehicle_type": "bike"}, {"bike_id": "bike_25660", "name": "4870", "lon": -71.41874333333334, "lat": 41.85249666666667, "is_reserved": 0, "is_disabled": 0, "jump_ebike_battery_level": "45%", "jump_vehicle_type": "bike"}, {"bike_id": "bike_25890", "name": "1293", "lon": -71.41571, "lat": 41.824776666666665, "is_reserved": 0, "is_disabled": 0, "jump_ebike_battery_level": "74%", "jump_vehicle_type": "bike"}, {"bike_id": "bike_25855", "name": "0888", "lon": -71.41942166666666, "lat": 41.799778333333336, "is_reserved": 0, "is_disabled": 0, "jump_ebike_battery_level": "46%", "jump_vehicle_type": "bike"}, {"bike_id": "bike_25752", "name": "3649", "lon": -71.41241666666667, "lat": 41.82975833333333, "is_reserved": 0, "is_disabled": 0, "jump_ebike_battery_level": "42%", "jump_vehicle_type": "bike"}, {"bike_id": "bike_25921", "name": "1483", "lon": -71.41263166666667, "lat": 41.81926333333333, "is_reserved": 0, "is_disabled": 0, "jump_ebike_battery_level": "42%", "jump_vehicle_type": "bike"}, {"bike_id": "bike_25650", "name": "4860", "lon": -71.41985833333334, "lat": 41.82516, "is_reserved": 0, "is_disabled": 0, "jump_ebike_battery_level": "79%", "jump_vehicle_type": "bike"}, {"bike_id": "bike_25603", "name": "3784", "lon": -71.42914166666667, "lat": 41.84653333333333, "is_reserved": 0, "is_disabled": 0, "jump_ebike_battery_level": "41%", "jump_vehicle_type": "bike"}, {"bike_id": "bike_25922", "name": "1485", "lon": -71.41267166666667, "lat": 41.829303333333336, "is_reserved": 0, "is_disabled": 0, "jump_ebike_battery_level": "51%", "jump_vehicle_type": "bike"}, {"bike_id": "bike_25892", "name": "1317", "lon": -71.41583333333334, "lat": 41.823568333333334, "is_reserved": 0, "is_disabled": 0, "jump_ebike_battery_level": "56%", "jump_vehicle_type": "bike"}, {"bike_id": "bike_25906", "name": "1373", "lon": -71.38681333333334, "lat": 41.82572, "is_reserved": 0, "is_disabled": 0, "jump_ebike_battery_level": "77%", "jump_vehicle_type": "bike"}, {"bike_id": "bike_25743", "name": "3640", "lon": -71.40631333333333, "lat": 41.83056333333333, "is_reserved": 0, "is_disabled": 0, "jump_ebike_battery_level": "77%", "jump_vehicle_type": "bike"}, {"bike_id": "bike_25767", "name": "3664", "lon": -71.40853333333334, "lat": 41.81206666666667, "is_reserved": 0, "is_disabled": 0, "jump_ebike_battery_level": "87%", "jump_vehicle_type": "bike"}, {"bike_id": "bike_25824", "name": "3721", "lon": -71.39032666666667, "lat": 41.78656333333333, "is_reserved": 0, "is_disabled": 0, "jump_ebike_battery_level": "51%", "jump_vehicle_type": "bike"}, {"bike_id": "bike_25640", "name": "4850", "lon": -71.40875166666666, "lat": 41.812015, "is_reserved": 0, "is_disabled": 0, "jump_ebike_battery_level": "87%", "jump_vehicle_type": "bike"}, {"bike_id": "bike_25856", "name": "0922", "lon": -71.41790333333333, "lat": 41.817146666666666, "is_reserved": 0, "is_disabled": 0, "jump_ebike_battery_level": "71%", "jump_vehicle_type": "bike"}, {"bike_id": "bike_26020", "name": "4886", "lon": -71.40127166666667, "lat": 41.83579666666667, "is_reserved": 0, "is_disabled": 0, "jump_ebike_battery_level": "41%", "jump_vehicle_type": "bike"}, {"bike_id": "bike_25816", "name": "3713", "lon": -71.41965333333333, "lat": 41.827785, "is_reserved": 0, "is_disabled": 0, "jump_ebike_battery_level": "44%", "jump_vehicle_type": "bike"}, {"bike_id": "bike_25887", "name": "1289", "lon": -71.397155, "lat": 41.833235, "is_reserved": 0, "is_disabled": 0, "jump_ebike_battery_level": "44%", "jump_vehicle_type": "bike"}, {"bike_id": "bike_25629", "name": "3810", "lon": -71.3962, "lat": 41.841166666666666, "is_reserved": 0, "is_disabled": 0, "jump_ebike_battery_level": "60%", "jump_vehicle_type": "bike"}, {"bike_id": "bike_25822", "name": "3719", "lon": -71.39431, "lat": 41.82750166666667, "is_reserved": 0, "is_disabled": 0, "jump_ebike_battery_level": "43%", "jump_vehicle_type": "bike"}, {"bike_id": "bike_25664", "name": "4874", "lon": -71.43140166666667, "lat": 41.81876666666667, "is_reserved": 0, "is_disabled": 0, "jump_ebike_battery_level": "55%", "jump_vehicle_type": "bike"}, {"bike_id": "bike_25653", "name": "4863", "lon": -71.39832166666666, "lat": 41.81960333333333, "is_reserved": 0, "is_disabled": 0, "jump_ebike_battery_level": "75%", "jump_vehicle_type": "bike"}, {"bike_id": "bike_25927", "name": "1302", "lon": -71.42495, "lat": 41.84614, "is_reserved": 0, "is_disabled": 0, "jump_ebike_battery_level": "46%", "jump_vehicle_type": "bike"}, {"bike_id": "bike_25745", "name": "3642", "lon": -71.39365, "lat": 41.830085, "is_reserved": 0, "is_disabled": 0, "jump_ebike_battery_level": "57%", "jump_vehicle_type": "bike"}, {"bike_id": "bike_25613", "name": "3794", "lon": -71.40142, "lat": 41.84036, "is_reserved": 0, "is_disabled": 0, "jump_ebike_battery_level": "66%", "jump_vehicle_type": "bike"}, {"bike_id": "bike_25639", "name": "4849", "lon": -71.38676833333334, "lat": 41.827685, "is_reserved": 0, "is_disabled": 0, "jump_ebike_battery_level": "41%", "jump_vehicle_type": "bike"}, {"bike_id": "bike_25728", "name": "3625", "lon": -71.42695166666667, "lat": 41.82257166666667, "is_reserved": 0, "is_disabled": 0, "jump_ebike_battery_level": "66%", "jump_vehicle_type": "bike"}, {"bike_id": "bike_25609", "name": "3790", "lon": -71.39489666666667, "lat": 41.83141166666667, "is_reserved": 0, "is_disabled": 0, "jump_ebike_battery_level": "73%", "jump_vehicle_type": "bike"}, {"bike_id": "bike_25788", "name": "3685", "lon": -71.39570166666667, "lat": 41.851906666666665, "is_reserved": 0, "is_disabled": 0, "jump_ebike_battery_level": "69%", "jump_vehicle_type": "bike"}, {"bike_id": "bike_25910", "name": "1385", "lon": -71.43394666666667, "lat": 41.813233333333336, "is_reserved": 0, "is_disabled": 0, "jump_ebike_battery_level": "60%", "jump_vehicle_type": "bike"}, {"bike_id": "bike_25902", "name": "1351", "lon": -71.40327666666667, "lat": 41.820458333333335, "is_reserved": 0, "is_disabled": 0, "jump_ebike_battery_level": "61%", "jump_vehicle_type": "bike"}, {"bike_id": "bike_26071", "name": "4937", "lon": -71.415925, "lat": 41.82486333333333, "is_reserved": 0, "is_disabled": 0, "jump_ebike_battery_level": "45%", "jump_vehicle_type": "bike"}, {"bike_id": "bike_25797", "name": "3694", "lon": -71.39740333333333, "lat": 41.832296666666664, "is_reserved": 0, "is_disabled": 0, "jump_ebike_battery_level": "48%", "jump_vehicle_type": "bike"}, {"bike_id": "bike_25929", "name": "1639", "lon": -71.41936333333334, "lat": 41.799818333333334, "is_reserved": 0, "is_disabled": 0, "jump_ebike_battery_level": "75%", "jump_vehicle_type": "bike"}, {"bike_id": "bike_26026", "name": "4892", "lon": -71.42207833333333, "lat": 41.80135666666666, "is_reserved": 0, "is_disabled": 0, "jump_ebike_battery_level": "42%", "jump_vehicle_type": "bike"}, {"bike_id": "bike_25631", "name": "3812", "lon": -71.42253666666667, "lat": 41.83308, "is_reserved": 0, "is_disabled": 0, "jump_ebike_battery_level": "68%", "jump_vehicle_type": "bike"}, {"bike_id": "bike_26029", "name": "4895", "lon": -71.438095, "lat": 41.8131, "is_reserved": 0, "is_disabled": 0, "jump_ebike_battery_level": "64%", "jump_vehicle_type": "bike"}, {"bike_id": "bike_25732", "name": "3629", "lon": -71.40070166666666, "lat": 41.821065, "is_reserved": 0, "is_disabled": 0, "jump_ebike_battery_level": "43%", "jump_vehicle_type": "bike"}, {"bike_id": "bike_25946", "name": "1565", "lon": -71.43230333333334, "lat": 41.81077, "is_reserved": 0, "is_disabled": 0, "jump_ebike_battery_level": "47%", "jump_vehicle_type": "bike"}, {"bike_id": "bike_25615", "name": "3796", "lon": -71.42493833333333, "lat": 41.83787, "is_reserved": 0, "is_disabled": 0, "jump_ebike_battery_level": "56%", "jump_vehicle_type": "bike"}, {"bike_id": "bike_25590", "name": "3771", "lon": -71.40411333333333, "lat": 41.83974166666667, "is_reserved": 0, "is_disabled": 0, "jump_ebike_battery_level": "57%", "jump_vehicle_type": "bike"}, {"bike_id": "bike_25580", "name": "3761", "lon": -71.40814, "lat": 41.83139333333333, "is_reserved": 0, "is_disabled": 0, "jump_ebike_battery_level": "69%", "jump_vehicle_type": "bike"}, {"bike_id": "bike_25656", "name": "4866", "lon": -71.42233333333333, "lat": 41.81458166666667, "is_reserved": 0, "is_disabled": 0, "jump_ebike_battery_level": "82%", "jump_vehicle_type": "bike"}, {"bike_id": "bike_25735", "name": "3632", "lon": -71.41567, "lat": 41.832633333333334, "is_reserved": 0, "is_disabled": 0, "jump_ebike_battery_level": "68%", "jump_vehicle_type": "bike"}, {"bike_id": "bike_25602", "name": "0027", "lon": -71.41927666666666, "lat": 41.82932666666667, "is_reserved": 0, "is_disabled": 0, "jump_ebike_battery_level": "70%", "jump_vehicle_type": "bike"}, {"bike_id": "bike_25818", "name": "3715", "lon": -71.40472333333334, "lat": 41.843445, "is_reserved": 0, "is_disabled": 0, "jump_ebike_battery_level": "53%", "jump_vehicle_type": "bike"}, {"bike_id": "bike_25754", "name": "3651", "lon": -71.40931666666667, "lat": 41.83632166666666, "is_reserved": 0, "is_disabled": 0, "jump_ebike_battery_level": "65%", "jump_vehicle_type": "bike"}, {"bike_id": "bike_26041", "name": "4907", "lon": -71.402595, "lat": 41.81905666666667, "is_reserved": 0, "is_disabled": 0, "jump_ebike_battery_level": "63%", "jump_vehicle_type": "bike"}, {"bike_id": "bike_25584", "name": "3765", "lon": -71.43498833333334, "lat": 41.8175, "is_reserved": 0, "is_disabled": 0, "jump_ebike_battery_level": "67%", "jump_vehicle_type": "bike"}, {"bike_id": "bike_25811", "name": "3708", "lon": -71.39429833333334, "lat": 41.831275, "is_reserved": 0, "is_disabled": 0, "jump_ebike_battery_level": "69%", "jump_vehicle_type": "bike"}, {"bike_id": "bike_25624", "name": "3805", "lon": -71.42485333333333, "lat": 41.867536666666666, "is_reserved": 0, "is_disabled": 0, "jump_ebike_battery_level": "38%", "jump_vehicle_type": "bike"}, {"bike_id": "bike_26057", "name": "4923", "lon": -71.42983166666667, "lat": 41.82425833333333, "is_reserved": 0, "is_disabled": 0, "jump_ebike_battery_level": "75%", "jump_vehicle_type": "bike"}, {"bike_id": "bike_25897", "name": "1634", "lon": -71.38191833333333, "lat": 41.827513333333336, "is_reserved": 0, "is_disabled": 0, "jump_ebike_battery_level": "56%", "jump_vehicle_type": "bike"}, {"bike_id": "bike_25952", "name": "1578", "lon": -71.40679833333333, "lat": 41.82763833333333, "is_reserved": 0, "is_disabled": 0, "jump_ebike_battery_level": "49%", "jump_vehicle_type": "bike"}, {"bike_id": "bike_25645", "name": "4855", "lon": -71.40585333333334, "lat": 41.82643, "is_reserved": 0, "is_disabled": 0, "jump_ebike_battery_level": "67%", "jump_vehicle_type": "bike"}, {"bike_id": "bike_25749", "name": "3646", "lon": -71.397005, "lat": 41.83110833333333, "is_reserved": 0, "is_disabled": 0, "jump_ebike_battery_level": "63%", "jump_vehicle_type": "bike"}, {"bike_id": "bike_25798", "name": "3695", "lon": -71.424925, "lat": 41.82493, "is_reserved": 0, "is_disabled": 0, "jump_ebike_battery_level": "65%", "jump_vehicle_type": "bike"}, {"bike_id": "bike_25860", "name": "1607", "lon": -71.42937, "lat": 41.809055, "is_reserved": 0, "is_disabled": 0, "jump_ebike_battery_level": "70%", "jump_vehicle_type": "bike"}, {"bike_id": "bike_25861", "name": "1029", "lon": -71.41002166666667, "lat": 41.815575, "is_reserved": 0, "is_disabled": 0, "jump_ebike_battery_level": "73%", "jump_vehicle_type": "bike"}, {"bike_id": "bike_26064", "name": "4930", "lon": -71.40724666666667, "lat": 41.828691666666664, "is_reserved": 0, "is_disabled": 0, "jump_ebike_battery_level": "60%", "jump_vehicle_type": "bike"}, {"bike_id": "bike_25605", "name": "3786", "lon": -71.42309166666666, "lat": 41.80853166666667, "is_reserved": 0, "is_disabled": 0, "jump_ebike_battery_level": "49%", "jump_vehicle_type": "bike"}, {"bike_id": "bike_26068", "name": "4934", "lon": -71.39149333333333, "lat": 41.82441333333333, "is_reserved": 0, "is_disabled": 0, "jump_ebike_battery_level": "75%", "jump_vehicle_type": "bike"}, {"bike_id": "bike_25753", "name": "3650", "lon": -71.40627666666667, "lat": 41.7798, "is_reserved": 0, "is_disabled": 0, "jump_ebike_battery_level": "43%", "jump_vehicle_type": "bike"}, {"bike_id": "bike_25607", "name": "3788", "lon": -71.40730833333333, "lat": 41.826843333333336, "is_reserved": 0, "is_disabled": 0, "jump_ebike_battery_level": "58%", "jump_vehicle_type": "bike"}, {"bike_id": "bike_25834", "name": "3731", "lon": -71.40195666666666, "lat": 41.818488333333335, "is_reserved": 0, "is_disabled": 0, "jump_ebike_battery_level": "47%", "jump_vehicle_type": "bike"}, {"bike_id": "bike_25750", "name": "3647", "lon": -71.43646, "lat": 41.838355, "is_reserved": 0, "is_disabled": 0, "jump_ebike_battery_level": "42%", "jump_vehicle_type": "bike"}, {"bike_id": "bike_25633", "name": "3814", "lon": -71.42937166666667, "lat": 41.81487, "is_reserved": 0, "is_disabled": 0, "jump_ebike_battery_level": "55%", "jump_vehicle_type": "bike"}, {"bike_id": "bike_25898", "name": "1340", "lon": -71.4014, "lat": 41.836506666666665, "is_reserved": 0, "is_disabled": 0, "jump_ebike_battery_level": "44%", "jump_vehicle_type": "bike"}, {"bike_id": "bike_25808", "name": "3705", "lon": -71.41377833333334, "lat": 41.825453333333336, "is_reserved": 0, "is_disabled": 0, "jump_ebike_battery_level": "55%", "jump_vehicle_type": "bike"}, {"bike_id": "bike_25622", "name": "3803", "lon": -71.38925, "lat": 41.817681666666665, "is_reserved": 0, "is_disabled": 0, "jump_ebike_battery_level": "84%", "jump_vehicle_type": "bike"}, {"bike_id": "bike_25646", "name": "4856", "lon": -71.39963166666666, "lat": 41.823585, "is_reserved": 0, "is_disabled": 0, "jump_ebike_battery_level": "72%", "jump_vehicle_type": "bike"}, {"bike_id": "bike_25829", "name": "3726", "lon": -71.41947666666667, "lat": 41.814745, "is_reserved": 0, "is_disabled": 0, "jump_ebike_battery_level": "49%", "jump_vehicle_type": "bike"}, {"bike_id": "bike_25872", "name": "1137", "lon": -71.40318333333333, "lat": 41.828855, "is_reserved": 0, "is_disabled": 0, "jump_ebike_battery_level": "83%", "jump_vehicle_type": "bike"}, {"bike_id": "bike_25759", "name": "3656", "lon": -71.41704333333334, "lat": 41.84552166666667, "is_reserved": 0, "is_disabled": 0, "jump_ebike_battery_level": "67%", "jump_vehicle_type": "bike"}, {"bike_id": "bike_25990", "name": "1637", "lon": -71.40069333333334, "lat": 41.82102833333333, "is_reserved": 0, "is_disabled": 0, "jump_ebike_battery_level": "49%", "jump_vehicle_type": "bike"}, {"bike_id": "bike_25823", "name": "3720", "lon": -71.41264666666666, "lat": 41.82935, "is_reserved": 0, "is_disabled": 0, "jump_ebike_battery_level": "46%", "jump_vehicle_type": "bike"}, {"bike_id": "bike_25758", "name": "3655", "lon": -71.44394166666666, "lat": 41.829335, "is_reserved": 0, "is_disabled": 0, "jump_ebike_battery_level": "60%", "jump_vehicle_type": "bike"}, {"bike_id": "bike_25630", "name": "3811", "lon": -71.41040666666666, "lat": 41.827645, "is_reserved": 0, "is_disabled": 0, "jump_ebike_battery_level": "40%", "jump_vehicle_type": "bike"}, {"bike_id": "bike_25793", "name": "3690", "lon": -71.39919333333333, "lat": 41.824041666666666, "is_reserved": 0, "is_disabled": 0, "jump_ebike_battery_level": "58%", "jump_vehicle_type": "bike"}, {"bike_id": "bike_132301", "name": "24480", "lon": -71.43340166666667, "lat": 41.84154, "is_reserved": 0, "is_disabled": 0, "jump_ebike_battery_level": "56%", "jump_vehicle_type": "bike"}, {"bike_id": "bike_134705", "name": "47878", "lon": -71.417755, "lat": 41.85891, "is_reserved": 0, "is_disabled": 0, "jump_ebike_battery_level": "52%", "jump_vehicle_type": "bike"}, {"bike_id": "bike_134727", "name": "44323", "lon": -71.42657833333334, "lat": 41.822918333333334, "is_reserved": 0, "is_disabled": 0, "jump_ebike_battery_level": "55%", "jump_vehicle_type": "bike"}, {"bike_id": "bike_133816", "name": "23144", "lon": -71.41539666666667, "lat": 41.828228333333335, "is_reserved": 0, "is_disabled": 0, "jump_ebike_battery_level": "70%", "jump_vehicle_type": "bike"}, {"bike_id": "bike_134515", "name": "23040", "lon": -71.41135666666666, "lat": 41.817141666666664, "is_reserved": 0, "is_disabled": 0, "jump_ebike_battery_level": "64%", "jump_vehicle_type": "bike"}, {"bike_id": "bike_134494", "name": "45034", "lon": -71.3948, "lat": 41.817793333333334, "is_reserved": 0, "is_disabled": 0, "jump_ebike_battery_level": "78%", "jump_vehicle_type": "bike"}, {"bike_id": "bike_134716", "name": "44532", "lon": -71.41589166666667, "lat": 41.812023333333336, "is_reserved": 0, "is_disabled": 0, "jump_ebike_battery_level": "53%", "jump_vehicle_type": "bike"}, {"bike_id": "bike_132282", "name": "24496", "lon": -71.403975, "lat": 41.840228333333336, "is_reserved": 0, "is_disabled": 0, "jump_ebike_battery_level": "69%", "jump_vehicle_type": "bike"}, {"bike_id": "bike_134537", "name": "23187", "lon": -71.40264833333333, "lat": 41.834865, "is_reserved": 0, "is_disabled": 0, "jump_ebike_battery_level": "51%", "jump_vehicle_type": "bike"}, {"bike_id": "bike_132316", "name": "24488", "lon": -71.41402166666667, "lat": 41.82199333333333, "is_reserved": 0, "is_disabled": 0, "jump_ebike_battery_level": "75%", "jump_vehicle_type": "bike"}, {"bike_id": "bike_133897", "name": "47707", "lon": -71.38953166666667, "lat": 41.82837166666667, "is_reserved": 0, "is_disabled": 0, "jump_ebike_battery_level": "44%", "jump_vehicle_type": "bike"}, {"bike_id": "bike_134697", "name": "44595", "lon": -71.41074166666667, "lat": 41.82760666666667, "is_reserved": 0, "is_disabled": 0, "jump_ebike_battery_level": "59%", "jump_vehicle_type": "bike"}, {"bike_id": "bike_134673", "name": "45228", "lon": -71.42482833333334, "lat": 41.83462, "is_reserved": 0, "is_disabled": 0, "jump_ebike_battery_level": "56%", "jump_vehicle_type": "bike"}, {"bike_id": "bike_134453", "name": "23045", "lon": -71.42666333333334, "lat": 41.819595, "is_reserved": 0, "is_disabled": 0, "jump_ebike_battery_level": "46%", "jump_vehicle_type": "bike"}, {"bike_id": "bike_133869", "name": "46480", "lon": -71.43010333333334, "lat": 41.819595, "is_reserved": 0, "is_disabled": 0, "jump_ebike_battery_level": "37%", "jump_vehicle_type": "bike"}, {"bike_id": "bike_134530", "name": "23076", "lon": -71.40553, "lat": 41.82180833333334, "is_reserved": 0, "is_disabled": 0, "jump_ebike_battery_level": "52%", "jump_vehicle_type": "bike"}, {"bike_id": "bike_133892", "name": "47720", "lon": -71.46536833333333, "lat": 41.843248333333335, "is_reserved": 0, "is_disabled": 0, "jump_ebike_battery_level": "86%", "jump_vehicle_type": "bike"}, {"bike_id": "bike_134755", "name": "23175", "lon": -71.41245833333333, "lat": 41.82928166666667, "is_reserved": 0, "is_disabled": 0, "jump_ebike_battery_level": "71%", "jump_vehicle_type": "bike"}, {"bike_id": "bike_132274", "name": "24472", "lon": -71.43197666666667, "lat": 41.822008333333336, "is_reserved": 0, "is_disabled": 0, "jump_ebike_battery_level": "60%", "jump_vehicle_type": "bike"}, {"bike_id": "bike_132835", "name": "22839", "lon": -83.12596166666667, "lat": 42.54933, "is_reserved": 0, "is_disabled": 0, "jump_ebike_battery_level": "36%", "jump_vehicle_type": "bike"}, {"bike_id": "bike_133856", "name": "20649", "lon": -71.46544166666666, "lat": 41.84326333333333, "is_reserved": 0, "is_disabled": 0, "jump_ebike_battery_level": "88%", "jump_vehicle_type": "bike"}, {"bike_id": "bike_134446", "name": "22860", "lon": -71.43255333333333, "lat": 41.82561833333333, "is_reserved": 0, "is_disabled": 0, "jump_ebike_battery_level": "78%", "jump_vehicle_type": "bike"}, {"bike_id": "bike_132310", "name": "24554", "lon": -71.40140833333334, "lat": 41.82465166666667, "is_reserved": 0, "is_disabled": 0, "jump_ebike_battery_level": "70%", "jump_vehicle_type": "bike"}, {"bike_id": "bike_134504", "name": "45035", "lon": -71.41830833333333, "lat": 41.80848833333334, "is_reserved": 0, "is_disabled": 0, "jump_ebike_battery_level": "70%", "jump_vehicle_type": "bike"}, {"bike_id": "bike_132255", "name": "24557", "lon": -71.39259, "lat": 41.824375, "is_reserved": 0, "is_disabled": 0, "jump_ebike_battery_level": "65%", "jump_vehicle_type": "bike"}, {"bike_id": "bike_134685", "name": "44590", "lon": -71.40655166666667, "lat": 41.84401166666667, "is_reserved": 0, "is_disabled": 0, "jump_ebike_battery_level": "85%", "jump_vehicle_type": "bike"}, {"bike_id": "bike_132804", "name": "24688", "lon": -83.126495, "lat": 42.54934, "is_reserved": 0, "is_disabled": 0, "jump_ebike_battery_level": "60%", "jump_vehicle_type": "bike"}, {"bike_id": "bike_132809", "name": "22927", "lon": -83.12639, "lat": 42.549303333333334, "is_reserved": 0, "is_disabled": 0, "jump_ebike_battery_level": "84%", "jump_vehicle_type": "bike"}, {"bike_id": "bike_133818", "name": "23151", "lon": -71.401425, "lat": 41.829053333333334, "is_reserved": 0, "is_disabled": 0, "jump_ebike_battery_level": "75%", "jump_vehicle_type": "bike"}, {"bike_id": "bike_132854", "name": "18995", "lon": -83.12633333333333, "lat": 42.55, "is_reserved": 0, "is_disabled": 0, "jump_ebike_battery_level": "43%", "jump_vehicle_type": "bike"}, {"bike_id": "bike_132869", "name": "22636", "lon": -83.12643833333334, "lat": 42.549305, "is_reserved": 0, "is_disabled": 0, "jump_ebike_battery_level": "84%", "jump_vehicle_type": "bike"}, {"bike_id": "bike_132290", "name": "24404", "lon": -71.40014166666667, "lat": 41.84141666666667, "is_reserved": 0, "is_disabled": 0, "jump_ebike_battery_level": "50%", "jump_vehicle_type": "bike"}, {"bike_id": "bike_134549", "name": "23146", "lon": -71.45972833333333, "lat": 41.832678333333334, "is_reserved": 0, "is_disabled": 0, "jump_ebike_battery_level": "66%", "jump_vehicle_type": "bike"}, {"bike_id": "bike_133483", "name": "44469", "lon": -71.46491, "lat": 41.84366333333333, "is_reserved": 0, "is_disabled": 0, "jump_ebike_battery_level": "87%", "jump_vehicle_type": "bike"}, {"bike_id": "bike_132072", "name": "44225", "lon": -83.12644333333333, "lat": 42.54934, "is_reserved": 0, "is_disabled": 0, "jump_ebike_battery_level": "39%", "jump_vehicle_type": "bike"}, {"bike_id": "bike_133405", "name": "22985", "lon": -83.12644666666667, "lat": 42.549323333333334, "is_reserved": 0, "is_disabled": 0, "jump_ebike_battery_level": "85%", "jump_vehicle_type": "bike"}, {"bike_id": "bike_133899", "name": "23000", "lon": -71.39675833333334, "lat": 41.82271333333333, "is_reserved": 0, "is_disabled": 0, "jump_ebike_battery_level": "83%", "jump_vehicle_type": "bike"}, {"bike_id": "bike_133881", "name": "23150", "lon": -71.43346333333334, "lat": 41.841544999999996, "is_reserved": 0, "is_disabled": 0, "jump_ebike_battery_level": "75%", "jump_vehicle_type": "bike"}, {"bike_id": "bike_132949", "name": "22883", "lon": -71.41473, "lat": 41.81173833333333, "is_reserved": 0, "is_disabled": 0, "jump_ebike_battery_level": "87%", "jump_vehicle_type": "bike"}, {"bike_id": "bike_131976", "name": "24667", "lon": -83.12653, "lat": 42.549325, "is_reserved": 0, "is_disabled": 0, "jump_ebike_battery_level": "49%", "jump_vehicle_type": "bike"}, {"bike_id": "bike_132088", "name": "44281", "lon": -83.126505, "lat": 42.55001333333333, "is_reserved": 0, "is_disabled": 0, "jump_ebike_battery_level": "68%", "jump_vehicle_type": "bike"}, {"bike_id": "bike_131522", "name": "22271", "lon": -83.12646333333333, "lat": 42.54939, "is_reserved": 0, "is_disabled": 0, "jump_ebike_battery_level": "71%", "jump_vehicle_type": "bike"}, {"bike_id": "bike_134478", "name": "23110", "lon": -71.43259166666667, "lat": 41.82561333333334, "is_reserved": 0, "is_disabled": 0, "jump_ebike_battery_level": "86%", "jump_vehicle_type": "bike"}, {"bike_id": "bike_133840", "name": "23147", "lon": -71.46490333333334, "lat": 41.8436, "is_reserved": 0, "is_disabled": 0, "jump_ebike_battery_level": "84%", "jump_vehicle_type": "bike"}, {"bike_id": "bike_132041", "name": "24634", "lon": -83.12663, "lat": 42.54960666666667, "is_reserved": 0, "is_disabled": 0, "jump_ebike_battery_level": "71%", "jump_vehicle_type": "bike"}, {"bike_id": "bike_132020", "name": "24635", "lon": -83.12649, "lat": 42.549346666666665, "is_reserved": 0, "is_disabled": 0, "jump_ebike_battery_level": "60%", "jump_vehicle_type": "bike"}, {"bike_id": "bike_133911", "name": "23120", "lon": -71.46436833333334, "lat": 41.842778333333335, "is_reserved": 0, "is_disabled": 0, "jump_ebike_battery_level": "81%", "jump_vehicle_type": "bike"}, {"bike_id": "bike_132948", "name": "22923", "lon": -83.12640833333333, "lat": 42.5494, "is_reserved": 0, "is_disabled": 0, "jump_ebike_battery_level": "84%", "jump_vehicle_type": "bike"}, {"bike_id": "bike_134471", "name": "22848", "lon": -71.40715666666667, "lat": 41.827173333333334, "is_reserved": 0, "is_disabled": 0, "jump_ebike_battery_level": "50%", "jump_vehicle_type": "bike"}, {"bike_id": "bike_132104", "name": "24493", "lon": -83.12646333333333, "lat": 42.54939, "is_reserved": 0, "is_disabled": 0, "jump_ebike_battery_level": "69%", "jump_vehicle_type": "bike"}, {"bike_id": "bike_133847", "name": "23065", "lon": -71.40669, "lat": 41.82693166666667, "is_reserved": 0, "is_disabled": 0, "jump_ebike_battery_level": "85%", "jump_vehicle_type": "bike"}, {"bike_id": "bike_132929", "name": "44252", "lon": -71.46637, "lat": 41.84202166666667, "is_reserved": 0, "is_disabled": 0, "jump_ebike_battery_level": "88%", "jump_vehicle_type": "bike"}, {"bike_id": "bike_132013", "name": "24653", "lon": -71.43262833333333, "lat": 41.82566666666666, "is_reserved": 0, "is_disabled": 0, "jump_ebike_battery_level": "87%", "jump_vehicle_type": "bike"}, {"bike_id": "bike_133920", "name": "23139", "lon": -71.42820666666667, "lat": 41.83470333333333, "is_reserved": 0, "is_disabled": 0, "jump_ebike_battery_level": "73%", "jump_vehicle_type": "bike"}, {"bike_id": "bike_133883", "name": "23067", "lon": -71.40653166666667, "lat": 41.79808166666667, "is_reserved": 0, "is_disabled": 0, "jump_ebike_battery_level": "60%", "jump_vehicle_type": "bike"}, {"bike_id": "bike_133927", "name": "22924", "lon": -83.12643333333334, "lat": 42.549353333333336, "is_reserved": 0, "is_disabled": 0, "jump_ebike_battery_level": "85%", "jump_vehicle_type": "bike"}, {"bike_id": "bike_133894", "name": "47704", "lon": -71.39953833333334, "lat": 41.82430333333333, "is_reserved": 0, "is_disabled": 0, "jump_ebike_battery_level": "83%", "jump_vehicle_type": "bike"}, {"bike_id": "bike_134649", "name": "44390", "lon": -71.40365666666666, "lat": 41.82531, "is_reserved": 0, "is_disabled": 0, "jump_ebike_battery_level": "69%", "jump_vehicle_type": "bike"}, {"bike_id": "bike_134674", "name": "44362", "lon": -71.401175, "lat": 41.823413333333335, "is_reserved": 0, "is_disabled": 0, "jump_ebike_battery_level": "61%", "jump_vehicle_type": "bike"}, {"bike_id": "bike_132247", "name": "22929", "lon": -83.126445, "lat": 42.549325, "is_reserved": 0, "is_disabled": 0, "jump_ebike_battery_level": "59%", "jump_vehicle_type": "bike"}, {"bike_id": "bike_133819", "name": "22994", "lon": -83.12645, "lat": 42.54933, "is_reserved": 0, "is_disabled": 0, "jump_ebike_battery_level": "86%", "jump_vehicle_type": "bike"}, {"bike_id": "bike_133912", "name": "22972", "lon": -71.40760166666666, "lat": 41.835251666666665, "is_reserved": 0, "is_disabled": 0, "jump_ebike_battery_level": "87%", "jump_vehicle_type": "bike"}, {"bike_id": "bike_132238", "name": "24434", "lon": -71.43260333333333, "lat": 41.82569, "is_reserved": 0, "is_disabled": 0, "jump_ebike_battery_level": "81%", "jump_vehicle_type": "bike"}, {"bike_id": "bike_132006", "name": "24578", "lon": -71.43264666666667, "lat": 41.82565833333334, "is_reserved": 0, "is_disabled": 0, "jump_ebike_battery_level": "77%", "jump_vehicle_type": "bike"}, {"bike_id": "bike_133867", "name": "23043", "lon": -71.40134, "lat": 41.835856666666665, "is_reserved": 0, "is_disabled": 0, "jump_ebike_battery_level": "76%", "jump_vehicle_type": "bike"}, {"bike_id": "bike_132270", "name": "19311", "lon": -83.12633333333333, "lat": 42.549166666666665, "is_reserved": 0, "is_disabled": 0, "jump_ebike_battery_level": "83%", "jump_vehicle_type": "bike"}, {"bike_id": "bike_133456", "name": "23132", "lon": -83.12639, "lat": 42.54927166666667, "is_reserved": 0, "is_disabled": 0, "jump_ebike_battery_level": "86%", "jump_vehicle_type": "bike"}, {"bike_id": "bike_132299", "name": "22887", "lon": -71.39261666666667, "lat": 41.821641666666665, "is_reserved": 0, "is_disabled": 0, "jump_ebike_battery_level": "63%", "jump_vehicle_type": "bike"}, {"bike_id": "bike_133845", "name": "47908", "lon": -71.446285, "lat": 41.824725, "is_reserved": 0, "is_disabled": 0, "jump_ebike_battery_level": "67%", "jump_vehicle_type": "bike"}, {"bike_id": "bike_132044", "name": "24648", "lon": -71.38675166666667, "lat": 41.825788333333335, "is_reserved": 0, "is_disabled": 0, "jump_ebike_battery_level": "79%", "jump_vehicle_type": "bike"}, {"bike_id": "bike_133878", "name": "23119", "lon": -71.39085666666666, "lat": 41.834475, "is_reserved": 0, "is_disabled": 0, "jump_ebike_battery_level": "80%", "jump_vehicle_type": "bike"}, {"bike_id": "bike_133889", "name": "47672", "lon": -71.39612666666666, "lat": 41.821345, "is_reserved": 0, "is_disabled": 0, "jump_ebike_battery_level": "51%", "jump_vehicle_type": "bike"}, {"bike_id": "bike_133503", "name": "22893", "lon": -71.40941333333333, "lat": 41.82803833333333, "is_reserved": 0, "is_disabled": 0, "jump_ebike_battery_level": "78%", "jump_vehicle_type": "bike"}, {"bike_id": "bike_132257", "name": "24491", "lon": -71.39949166666666, "lat": 41.82828166666667, "is_reserved": 0, "is_disabled": 0, "jump_ebike_battery_level": "80%", "jump_vehicle_type": "bike"}, {"bike_id": "bike_134686", "name": "44557", "lon": -71.39021166666667, "lat": 41.83684, "is_reserved": 0, "is_disabled": 0, "jump_ebike_battery_level": "85%", "jump_vehicle_type": "bike"}, {"bike_id": "bike_133479", "name": "20491", "lon": -83.12633333333333, "lat": 42.549166666666665, "is_reserved": 0, "is_disabled": 0, "jump_ebike_battery_level": "50%", "jump_vehicle_type": "bike"}, {"bike_id": "bike_134742", "name": "44313", "lon": -71.40292833333334, "lat": 41.82468, "is_reserved": 0, "is_disabled": 0, "jump_ebike_battery_level": "78%", "jump_vehicle_type": "bike"}, {"bike_id": "bike_132321", "name": "24530", "lon": -71.42038833333334, "lat": 41.83205, "is_reserved": 0, "is_disabled": 0, "jump_ebike_battery_level": "84%", "jump_vehicle_type": "bike"}, {"bike_id": "bike_134666", "name": "44546", "lon": -71.42050666666667, "lat": 41.809531666666665, "is_reserved": 0, "is_disabled": 0, "jump_ebike_battery_level": "51%", "jump_vehicle_type": "bike"}, {"bike_id": "bike_134454", "name": "44289", "lon": -71.43284166666666, "lat": 41.825715, "is_reserved": 0, "is_disabled": 0, "jump_ebike_battery_level": "81%", "jump_vehicle_type": "bike"}, {"bike_id": "bike_132295", "name": "24499", "lon": -71.41474333333333, "lat": 41.81861333333333, "is_reserved": 0, "is_disabled": 0, "jump_ebike_battery_level": "78%", "jump_vehicle_type": "bike"}, {"bike_id": "bike_134684", "name": "44321", "lon": -71.40152, "lat": 41.82922333333333, "is_reserved": 0, "is_disabled": 0, "jump_ebike_battery_level": "47%", "jump_vehicle_type": "bike"}, {"bike_id": "bike_133416", "name": "44422", "lon": -71.39930666666666, "lat": 41.82407166666667, "is_reserved": 0, "is_disabled": 0, "jump_ebike_battery_level": "87%", "jump_vehicle_type": "bike"}, {"bike_id": "bike_134543", "name": "23042", "lon": -71.40716, "lat": 41.826373333333336, "is_reserved": 0, "is_disabled": 0, "jump_ebike_battery_level": "42%", "jump_vehicle_type": "bike"}, {"bike_id": "bike_134490", "name": "44398", "lon": -71.41560833333334, "lat": 41.819858333333336, "is_reserved": 0, "is_disabled": 0, "jump_ebike_battery_level": "64%", "jump_vehicle_type": "bike"}, {"bike_id": "bike_132077", "name": "24695", "lon": -71.42693, "lat": 41.82121166666667, "is_reserved": 0, "is_disabled": 0, "jump_ebike_battery_level": "55%", "jump_vehicle_type": "bike"}, {"bike_id": "bike_134691", "name": "44419", "lon": -71.44810666666666, "lat": 41.82067833333333, "is_reserved": 0, "is_disabled": 0, "jump_ebike_battery_level": "81%", "jump_vehicle_type": "bike"}, {"bike_id": "bike_134483", "name": "23022", "lon": -71.40715666666667, "lat": 41.82451666666667, "is_reserved": 0, "is_disabled": 0, "jump_ebike_battery_level": "62%", "jump_vehicle_type": "bike"}, {"bike_id": "bike_133907", "name": "23143", "lon": -71.40827, "lat": 41.828671666666665, "is_reserved": 0, "is_disabled": 0, "jump_ebike_battery_level": "45%", "jump_vehicle_type": "bike"}, {"bike_id": "bike_132289", "name": "24489", "lon": -71.39149833333333, "lat": 41.83581, "is_reserved": 0, "is_disabled": 0, "jump_ebike_battery_level": "69%", "jump_vehicle_type": "bike"}, {"bike_id": "bike_132293", "name": "24509", "lon": -71.41086166666666, "lat": 41.82424833333334, "is_reserved": 0, "is_disabled": 0, "jump_ebike_battery_level": "69%", "jump_vehicle_type": "bike"}, {"bike_id": "bike_134669", "name": "45263", "lon": -71.40775833333333, "lat": 41.83575666666667, "is_reserved": 0, "is_disabled": 0, "jump_ebike_battery_level": "63%", "jump_vehicle_type": "bike"}, {"bike_id": "bike_134750", "name": "44340", "lon": -71.404675, "lat": 41.82584333333333, "is_reserved": 0, "is_disabled": 0, "jump_ebike_battery_level": "77%", "jump_vehicle_type": "bike"}, {"bike_id": "bike_134693", "name": "44298", "lon": -71.40668333333333, "lat": 41.83948, "is_reserved": 0, "is_disabled": 0, "jump_ebike_battery_level": "72%", "jump_vehicle_type": "bike"}, {"bike_id": "bike_134736", "name": "44425", "lon": -71.406025, "lat": 41.82321833333334, "is_reserved": 0, "is_disabled": 0, "jump_ebike_battery_level": "39%", "jump_vehicle_type": "bike"}, {"bike_id": "bike_134723", "name": "45197", "lon": -71.39735833333333, "lat": 41.82315833333333, "is_reserved": 0, "is_disabled": 0, "jump_ebike_battery_level": "76%", "jump_vehicle_type": "bike"}, {"bike_id": "bike_134445", "name": "22861", "lon": -71.39863666666666, "lat": 41.8535, "is_reserved": 0, "is_disabled": 0, "jump_ebike_battery_level": "56%", "jump_vehicle_type": "bike"}, {"bike_id": "bike_134449", "name": "23190", "lon": -71.411435, "lat": 41.82163, "is_reserved": 0, "is_disabled": 0, "jump_ebike_battery_level": "52%", "jump_vehicle_type": "bike"}, {"bike_id": "bike_134527", "name": "44257", "lon": -71.43893666666666, "lat": 41.823258333333335, "is_reserved": 0, "is_disabled": 0, "jump_ebike_battery_level": "38%", "jump_vehicle_type": "bike"}, {"bike_id": "bike_134720", "name": "45233", "lon": -71.38832833333333, "lat": 41.828536666666665, "is_reserved": 0, "is_disabled": 0, "jump_ebike_battery_level": "40%", "jump_vehicle_type": "bike"}, {"bike_id": "bike_134656", "name": "44332", "lon": -71.42908, "lat": 41.82281833333333, "is_reserved": 0, "is_disabled": 0, "jump_ebike_battery_level": "67%", "jump_vehicle_type": "bike"}, {"bike_id": "bike_134467", "name": "23074", "lon": -71.40565, "lat": 41.78822666666667, "is_reserved": 0, "is_disabled": 0, "jump_ebike_battery_level": "66%", "jump_vehicle_type": "bike"}, {"bike_id": "bike_134740", "name": "44455", "lon": -71.41153166666666, "lat": 41.815796666666664, "is_reserved": 0, "is_disabled": 0, "jump_ebike_battery_level": "70%", "jump_vehicle_type": "bike"}, {"bike_id": "bike_131582", "name": "47338", "lon": -71.45528666666667, "lat": 41.812796666666664, "is_reserved": 0, "is_disabled": 0, "jump_ebike_battery_level": "71%", "jump_vehicle_type": "bike"}, {"bike_id": "bike_134461", "name": "44600", "lon": -71.396075, "lat": 41.788855, "is_reserved": 0, "is_disabled": 0, "jump_ebike_battery_level": "65%", "jump_vehicle_type": "bike"}, {"bike_id": "bike_133893", "name": "47748", "lon": -71.43915, "lat": 41.824655, "is_reserved": 0, "is_disabled": 0, "jump_ebike_battery_level": "40%", "jump_vehicle_type": "bike"}, {"bike_id": "bike_134547", "name": "23053", "lon": -71.406565, "lat": 41.83356, "is_reserved": 0, "is_disabled": 0, "jump_ebike_battery_level": "44%", "jump_vehicle_type": "bike"}, {"bike_id": "bike_134442", "name": "22869", "lon": -71.45964833333333, "lat": 41.82407833333333, "is_reserved": 0, "is_disabled": 0, "jump_ebike_battery_level": "75%", "jump_vehicle_type": "bike"}, {"bike_id": "bike_134733", "name": "47877", "lon": -71.44511, "lat": 41.84329666666667, "is_reserved": 0, "is_disabled": 0, "jump_ebike_battery_level": "36%", "jump_vehicle_type": "bike"}, {"bike_id": "bike_134488", "name": "45380", "lon": -71.41339833333333, "lat": 41.81966666666667, "is_reserved": 0, "is_disabled": 0, "jump_ebike_battery_level": "51%", "jump_vehicle_type": "bike"}, {"bike_id": "bike_132287", "name": "19023", "lon": -71.44632166666666, "lat": 41.83144, "is_reserved": 0, "is_disabled": 0, "jump_ebike_battery_level": "78%", "jump_vehicle_type": "bike"}, {"bike_id": "bike_132296", "name": "24517", "lon": -71.46595833333333, "lat": 41.83363333333333, "is_reserved": 0, "is_disabled": 0, "jump_ebike_battery_level": "44%", "jump_vehicle_type": "bike"}, {"bike_id": "bike_134510", "name": "23038", "lon": -71.412005, "lat": 41.80441666666667, "is_reserved": 0, "is_disabled": 0, "jump_ebike_battery_level": "85%", "jump_vehicle_type": "bike"}, {"bike_id": "bike_133902", "name": "23129", "lon": -71.39843833333333, "lat": 41.829885, "is_reserved": 0, "is_disabled": 0, "jump_ebike_battery_level": "89%", "jump_vehicle_type": "bike"}, {"bike_id": "bike_134707", "name": "44697", "lon": -71.39561, "lat": 41.847746666666666, "is_reserved": 0, "is_disabled": 0, "jump_ebike_battery_level": "50%", "jump_vehicle_type": "bike"}, {"bike_id": "bike_134644", "name": "44343", "lon": -71.40916333333334, "lat": 41.805398333333336, "is_reserved": 0, "is_disabled": 0, "jump_ebike_battery_level": "74%", "jump_vehicle_type": "bike"}, {"bike_id": "bike_133916", "name": "23124", "lon": -71.409835, "lat": 41.816613333333336, "is_reserved": 0, "is_disabled": 0, "jump_ebike_battery_level": "41%", "jump_vehicle_type": "bike"}, {"bike_id": "bike_134748", "name": "44527", "lon": -71.45084333333334, "lat": 41.84732666666667, "is_reserved": 0, "is_disabled": 0, "jump_ebike_battery_level": "45%", "jump_vehicle_type": "bike"}, {"bike_id": "bike_134675", "name": "45193", "lon": -71.39914166666667, "lat": 41.8195, "is_reserved": 0, "is_disabled": 0, "jump_ebike_battery_level": "54%", "jump_vehicle_type": "bike"}, {"bike_id": "bike_134528", "name": "23174", "lon": -71.42949333333334, "lat": 41.82381, "is_reserved": 0, "is_disabled": 0, "jump_ebike_battery_level": "51%", "jump_vehicle_type": "bike"}, {"bike_id": "bike_134526", "name": "23082", "lon": -71.40664, "lat": 41.82705833333333, "is_reserved": 0, "is_disabled": 0, "jump_ebike_battery_level": "69%", "jump_vehicle_type": "bike"}, {"bike_id": "bike_134706", "name": "44435", "lon": -71.42072666666667, "lat": 41.836488333333335, "is_reserved": 0, "is_disabled": 0, "jump_ebike_battery_level": "60%", "jump_vehicle_type": "bike"}, {"bike_id": "bike_134542", "name": "22998", "lon": -71.39441333333333, "lat": 41.83134, "is_reserved": 0, "is_disabled": 0, "jump_ebike_battery_level": "52%", "jump_vehicle_type": "bike"}, {"bike_id": "bike_133923", "name": "23093", "lon": -71.40349, "lat": 41.82666666666667, "is_reserved": 0, "is_disabled": 0, "jump_ebike_battery_level": "77%", "jump_vehicle_type": "bike"}, {"bike_id": "bike_134499", "name": "44576", "lon": -71.40626, "lat": 41.82680666666667, "is_reserved": 0, "is_disabled": 0, "jump_ebike_battery_level": "65%", "jump_vehicle_type": "bike"}, {"bike_id": "bike_132258", "name": "24546", "lon": -71.416835, "lat": 41.81088666666667, "is_reserved": 0, "is_disabled": 0, "jump_ebike_battery_level": "58%", "jump_vehicle_type": "bike"}, {"bike_id": "bike_134741", "name": "44307", "lon": -71.38889, "lat": 41.82215, "is_reserved": 0, "is_disabled": 0, "jump_ebike_battery_level": "44%", "jump_vehicle_type": "bike"}, {"bike_id": "bike_134535", "name": "23077", "lon": -71.39105, "lat": 41.82302833333333, "is_reserved": 0, "is_disabled": 0, "jump_ebike_battery_level": "63%", "jump_vehicle_type": "bike"}, {"bike_id": "bike_134533", "name": "45081", "lon": -71.38534833333334, "lat": 41.83467, "is_reserved": 0, "is_disabled": 0, "jump_ebike_battery_level": "48%", "jump_vehicle_type": "bike"}, {"bike_id": "bike_134712", "name": "44402", "lon": -71.40430833333333, "lat": 41.837653333333336, "is_reserved": 0, "is_disabled": 0, "jump_ebike_battery_level": "45%", "jump_vehicle_type": "bike"}, {"bike_id": "bike_134743", "name": "44327", "lon": -71.42645, "lat": 41.797695, "is_reserved": 0, "is_disabled": 0, "jump_ebike_battery_level": "59%", "jump_vehicle_type": "bike"}, {"bike_id": "bike_134517", "name": "45095", "lon": -71.438925, "lat": 41.823411666666665, "is_reserved": 0, "is_disabled": 0, "jump_ebike_battery_level": "66%", "jump_vehicle_type": "bike"}, {"bike_id": "bike_134709", "name": "44303", "lon": -71.39245166666667, "lat": 41.84406, "is_reserved": 0, "is_disabled": 0, "jump_ebike_battery_level": "81%", "jump_vehicle_type": "bike"}, {"bike_id": "bike_134539", "name": "23071", "lon": -71.40954, "lat": 41.805321666666664, "is_reserved": 0, "is_disabled": 0, "jump_ebike_battery_level": "63%", "jump_vehicle_type": "bike"}, {"bike_id": "bike_133839", "name": "22873", "lon": -71.37087333333334, "lat": 41.81384166666667, "is_reserved": 0, "is_disabled": 0, "jump_ebike_battery_level": "48%", "jump_vehicle_type": "bike"}, {"bike_id": "bike_134739", "name": "44344", "lon": -71.42902833333333, "lat": 41.822905, "is_reserved": 0, "is_disabled": 0, "jump_ebike_battery_level": "66%", "jump_vehicle_type": "bike"}, {"bike_id": "bike_134472", "name": "45031", "lon": -71.409415, "lat": 41.800133333333335, "is_reserved": 0, "is_disabled": 0, "jump_ebike_battery_level": "75%", "jump_vehicle_type": "bike"}, {"bike_id": "bike_134689", "name": "45363", "lon": -71.45508, "lat": 41.824783333333336, "is_reserved": 0, "is_disabled": 0, "jump_ebike_battery_level": "53%", "jump_vehicle_type": "bike"}, {"bike_id": "bike_134725", "name": "44373", "lon": -71.43243333333334, "lat": 41.808508333333336, "is_reserved": 0, "is_disabled": 0, "jump_ebike_battery_level": "53%", "jump_vehicle_type": "bike"}, {"bike_id": "bike_132261", "name": "24448", "lon": -71.414865, "lat": 41.8185, "is_reserved": 0, "is_disabled": 0, "jump_ebike_battery_level": "73%", "jump_vehicle_type": "bike"}, {"bike_id": "bike_134654", "name": "44352", "lon": -71.41574666666666, "lat": 41.823523333333334, "is_reserved": 0, "is_disabled": 0, "jump_ebike_battery_level": "61%", "jump_vehicle_type": "bike"}, {"bike_id": "bike_134676", "name": "44322", "lon": -71.40299666666667, "lat": 41.82286166666667, "is_reserved": 0, "is_disabled": 0, "jump_ebike_battery_level": "72%", "jump_vehicle_type": "bike"}, {"bike_id": "bike_134551", "name": "45032", "lon": -71.42030166666666, "lat": 41.79519166666667, "is_reserved": 0, "is_disabled": 0, "jump_ebike_battery_level": "42%", "jump_vehicle_type": "bike"}, {"bike_id": "bike_134667", "name": "45196", "lon": -71.44633666666667, "lat": 41.83146333333333, "is_reserved": 0, "is_disabled": 0, "jump_ebike_battery_level": "47%", "jump_vehicle_type": "bike"}, {"bike_id": "bike_132311", "name": "24552", "lon": -71.42050166666667, "lat": 41.80948, "is_reserved": 0, "is_disabled": 0, "jump_ebike_battery_level": "53%", "jump_vehicle_type": "bike"}, {"bike_id": "bike_134682", "name": "44462", "lon": -71.40253333333334, "lat": 41.830025, "is_reserved": 0, "is_disabled": 0, "jump_ebike_battery_level": "81%", "jump_vehicle_type": "bike"}, {"bike_id": "bike_134745", "name": "44438", "lon": -71.41616833333333, "lat": 41.805278333333334, "is_reserved": 0, "is_disabled": 0, "jump_ebike_battery_level": "62%", "jump_vehicle_type": "bike"}, {"bike_id": "bike_133913", "name": "23138", "lon": -71.40697333333334, "lat": 41.79302833333333, "is_reserved": 0, "is_disabled": 0, "jump_ebike_battery_level": "80%", "jump_vehicle_type": "bike"}, {"bike_id": "bike_133884", "name": "23030", "lon": -71.39283, "lat": 41.82086833333334, "is_reserved": 0, "is_disabled": 0, "jump_ebike_battery_level": "69%", "jump_vehicle_type": "bike"}, {"bike_id": "bike_134516", "name": "23079", "lon": -71.38691833333333, "lat": 41.82596, "is_reserved": 0, "is_disabled": 0, "jump_ebike_battery_level": "55%", "jump_vehicle_type": "bike"}, {"bike_id": "bike_133863", "name": "22872", "lon": -71.38623666666666, "lat": 41.827915, "is_reserved": 0, "is_disabled": 0, "jump_ebike_battery_level": "73%", "jump_vehicle_type": "bike"}, {"bike_id": "bike_134702", "name": "44555", "lon": -71.399315, "lat": 41.86247, "is_reserved": 0, "is_disabled": 0, "jump_ebike_battery_level": "86%", "jump_vehicle_type": "bike"}, {"bike_id": "bike_134455", "name": "44319", "lon": -71.400145, "lat": 41.82416666666667, "is_reserved": 0, "is_disabled": 0, "jump_ebike_battery_level": "49%", "jump_vehicle_type": "bike"}, {"bike_id": "bike_131578", "name": "22105", "lon": -71.41831666666667, "lat": 41.831781666666664, "is_reserved": 0, "is_disabled": 0, "jump_ebike_battery_level": "59%", "jump_vehicle_type": "bike"}, {"bike_id": "bike_132319", "name": "22900", "lon": -71.40293, "lat": 41.81926833333333, "is_reserved": 0, "is_disabled": 0, "jump_ebike_battery_level": "44%", "jump_vehicle_type": "bike"}, {"bike_id": "bike_134541", "name": "23188", "lon": -71.430205, "lat": 41.851146666666665, "is_reserved": 0, "is_disabled": 0, "jump_ebike_battery_level": "72%", "jump_vehicle_type": "bike"}, {"bike_id": "bike_134699", "name": "44333", "lon": -71.41569833333334, "lat": 41.8007, "is_reserved": 0, "is_disabled": 0, "jump_ebike_battery_level": "81%", "jump_vehicle_type": "bike"}, {"bike_id": "bike_134710", "name": "44548", "lon": -71.407355, "lat": 41.792748333333336, "is_reserved": 0, "is_disabled": 0, "jump_ebike_battery_level": "40%", "jump_vehicle_type": "bike"}, {"bike_id": "bike_134487", "name": "22870", "lon": -71.43899833333333, "lat": 41.823238333333336, "is_reserved": 0, "is_disabled": 0, "jump_ebike_battery_level": "68%", "jump_vehicle_type": "bike"}, {"bike_id": "bike_133915", "name": "47885", "lon": -71.39940333333334, "lat": 41.832966666666664, "is_reserved": 0, "is_disabled": 0, "jump_ebike_battery_level": "70%", "jump_vehicle_type": "bike"}, {"bike_id": "bike_134752", "name": "44472", "lon": -71.41938, "lat": 41.79981, "is_reserved": 0, "is_disabled": 0, "jump_ebike_battery_level": "71%", "jump_vehicle_type": "bike"}, {"bike_id": "bike_134498", "name": "45082", "lon": -71.413425, "lat": 41.83974666666667, "is_reserved": 0, "is_disabled": 0, "jump_ebike_battery_level": "83%", "jump_vehicle_type": "bike"}, {"bike_id": "bike_134701", "name": "44306", "lon": -71.38579333333334, "lat": 41.82756166666667, "is_reserved": 0, "is_disabled": 0, "jump_ebike_battery_level": "46%", "jump_vehicle_type": "bike"}, {"bike_id": "bike_134450", "name": "22849", "lon": -71.42429833333334, "lat": 41.84383166666667, "is_reserved": 0, "is_disabled": 0, "jump_ebike_battery_level": "46%", "jump_vehicle_type": "bike"}, {"bike_id": "bike_134448", "name": "22862", "lon": -71.41097, "lat": 41.833351666666665, "is_reserved": 0, "is_disabled": 0, "jump_ebike_battery_level": "45%", "jump_vehicle_type": "bike"}, {"bike_id": "bike_134536", "name": "23041", "lon": -71.38885, "lat": 41.822206666666666, "is_reserved": 0, "is_disabled": 0, "jump_ebike_battery_level": "44%", "jump_vehicle_type": "bike"}, {"bike_id": "bike_134652", "name": "44357", "lon": -71.410965, "lat": 41.800351666666664, "is_reserved": 0, "is_disabled": 0, "jump_ebike_battery_level": "85%", "jump_vehicle_type": "bike"}, {"bike_id": "bike_132941", "name": "23324", "lon": -71.426055, "lat": 41.83916333333333, "is_reserved": 0, "is_disabled": 0, "jump_ebike_battery_level": "69%", "jump_vehicle_type": "bike"}, {"bike_id": "bike_132303", "name": "24503", "lon": -71.413275, "lat": 41.825918333333334, "is_reserved": 0, "is_disabled": 0, "jump_ebike_battery_level": "73%", "jump_vehicle_type": "bike"}, {"bike_id": "bike_134722", "name": "45242", "lon": -71.39900333333334, "lat": 41.81848333333333, "is_reserved": 0, "is_disabled": 0, "jump_ebike_battery_level": "61%", "jump_vehicle_type": "bike"}, {"bike_id": "bike_131541", "name": "22080", "lon": -71.42676833333333, "lat": 41.84473, "is_reserved": 0, "is_disabled": 0, "jump_ebike_battery_level": "46%", "jump_vehicle_type": "bike"}, {"bike_id": "bike_134532", "name": "45080", "lon": -71.42187666666666, "lat": 41.82154333333333, "is_reserved": 0, "is_disabled": 0, "jump_ebike_battery_level": "53%", "jump_vehicle_type": "bike"}, {"bike_id": "bike_134704", "name": "44533", "lon": -71.40154, "lat": 41.803015, "is_reserved": 0, "is_disabled": 0, "jump_ebike_battery_level": "68%", "jump_vehicle_type": "bike"}, {"bike_id": "bike_133909", "name": "22982", "lon": -71.39529, "lat": 41.81983666666667, "is_reserved": 0, "is_disabled": 0, "jump_ebike_battery_level": "70%", "jump_vehicle_type": "bike"}, {"bike_id": "bike_133512", "name": "22892", "lon": -71.41583333333334, "lat": 41.827198333333335, "is_reserved": 0, "is_disabled": 0, "jump_ebike_battery_level": "80%", "jump_vehicle_type": "bike"}, {"bike_id": "bike_134700", "name": "44335", "lon": -71.39994, "lat": 41.82709833333333, "is_reserved": 0, "is_disabled": 0, "jump_ebike_battery_level": "69%", "jump_vehicle_type": "bike"}, {"bike_id": "bike_134540", "name": "22987", "lon": -71.41154333333333, "lat": 41.851575, "is_reserved": 0, "is_disabled": 0, "jump_ebike_battery_level": "82%", "jump_vehicle_type": "bike"}, {"bike_id": "bike_134474", "name": "44577", "lon": -71.38683666666667, "lat": 41.82572833333333, "is_reserved": 0, "is_disabled": 0, "jump_ebike_battery_level": "75%", "jump_vehicle_type": "bike"}, {"bike_id": "bike_134502", "name": "44315", "lon": -71.42679166666667, "lat": 41.829766666666664, "is_reserved": 0, "is_disabled": 0, "jump_ebike_battery_level": "40%", "jump_vehicle_type": "bike"}, {"bike_id": "bike_134653", "name": "45239", "lon": -71.39849166666667, "lat": 41.83206666666667, "is_reserved": 0, "is_disabled": 0, "jump_ebike_battery_level": "77%", "jump_vehicle_type": "bike"}, {"bike_id": "bike_134477", "name": "22847", "lon": -71.44225666666667, "lat": 41.824146666666664, "is_reserved": 0, "is_disabled": 0, "jump_ebike_battery_level": "58%", "jump_vehicle_type": "bike"}, {"bike_id": "bike_134508", "name": "22857", "lon": -71.41578666666666, "lat": 41.821345, "is_reserved": 0, "is_disabled": 0, "jump_ebike_battery_level": "74%", "jump_vehicle_type": "bike"}, {"bike_id": "bike_134447", "name": "23154", "lon": -71.41579166666666, "lat": 41.82069166666667, "is_reserved": 0, "is_disabled": 0, "jump_ebike_battery_level": "69%", "jump_vehicle_type": "bike"}, {"bike_id": "bike_134759", "name": "47897", "lon": -71.39832666666666, "lat": 41.81924, "is_reserved": 0, "is_disabled": 0, "jump_ebike_battery_level": "78%", "jump_vehicle_type": "bike"}, {"bike_id": "bike_134505", "name": "45107", "lon": -71.40927833333333, "lat": 41.81095166666667, "is_reserved": 0, "is_disabled": 0, "jump_ebike_battery_level": "71%", "jump_vehicle_type": "bike"}, {"bike_id": "bike_134513", "name": "44449", "lon": -71.39586666666666, "lat": 41.842315, "is_reserved": 0, "is_disabled": 0, "jump_ebike_battery_level": "78%", "jump_vehicle_type": "bike"}, {"bike_id": "bike_134636", "name": "45246", "lon": -71.412535, "lat": 41.816785, "is_reserved": 0, "is_disabled": 0, "jump_ebike_battery_level": "47%", "jump_vehicle_type": "bike"}, {"bike_id": "bike_134452", "name": "23035", "lon": -71.43249166666666, "lat": 41.83707833333333, "is_reserved": 0, "is_disabled": 0, "jump_ebike_battery_level": "89%", "jump_vehicle_type": "bike"}, {"bike_id": "bike_134512", "name": "44539", "lon": -71.42847666666667, "lat": 41.804915, "is_reserved": 0, "is_disabled": 0, "jump_ebike_battery_level": "58%", "jump_vehicle_type": "bike"}, {"bike_id": "bike_134680", "name": "45253", "lon": -71.41279666666667, "lat": 41.819388333333336, "is_reserved": 0, "is_disabled": 0, "jump_ebike_battery_level": "66%", "jump_vehicle_type": "bike"}, {"bike_id": "bike_134463", "name": "22971", "lon": -71.39429833333334, "lat": 41.83457166666667, "is_reserved": 0, "is_disabled": 0, "jump_ebike_battery_level": "80%", "jump_vehicle_type": "bike"}, {"bike_id": "bike_132253", "name": "24506", "lon": -71.415585, "lat": 41.825275, "is_reserved": 0, "is_disabled": 0, "jump_ebike_battery_level": "49%", "jump_vehicle_type": "bike"}, {"bike_id": "bike_134754", "name": "23159", "lon": -71.39423833333333, "lat": 41.83907166666667, "is_reserved": 0, "is_disabled": 0, "jump_ebike_battery_level": "46%", "jump_vehicle_type": "bike"}, {"bike_id": "bike_134534", "name": "23172", "lon": -71.39404666666667, "lat": 41.854778333333336, "is_reserved": 0, "is_disabled": 0, "jump_ebike_battery_level": "51%", "jump_vehicle_type": "bike"}, {"bike_id": "bike_134519", "name": "22992", "lon": -71.41227833333333, "lat": 41.82503833333333, "is_reserved": 0, "is_disabled": 0, "jump_ebike_battery_level": "67%", "jump_vehicle_type": "bike"}, {"bike_id": "bike_134749", "name": "45210", "lon": -71.42684166666666, "lat": 41.82362666666667, "is_reserved": 0, "is_disabled": 0, "jump_ebike_battery_level": "59%", "jump_vehicle_type": "bike"}, {"bike_id": "bike_133900", "name": "22851", "lon": -71.40652666666666, "lat": 41.833575, "is_reserved": 0, "is_disabled": 0, "jump_ebike_battery_level": "60%", "jump_vehicle_type": "bike"}, {"bike_id": "bike_134462", "name": "23160", "lon": -71.42332666666667, "lat": 41.81495833333334, "is_reserved": 0, "is_disabled": 0, "jump_ebike_battery_level": "45%", "jump_vehicle_type": "bike"}, {"bike_id": "bike_133849", "name": "23056", "lon": -71.39718666666667, "lat": 41.820123333333335, "is_reserved": 0, "is_disabled": 0, "jump_ebike_battery_level": "72%", "jump_vehicle_type": "bike"}, {"bike_id": "bike_134664", "name": "44436", "lon": -71.40276, "lat": 41.83436, "is_reserved": 0, "is_disabled": 0, "jump_ebike_battery_level": "66%", "jump_vehicle_type": "bike"}, {"bike_id": "bike_134677", "name": "44471", "lon": -71.41560666666666, "lat": 41.82581, "is_reserved": 0, "is_disabled": 0, "jump_ebike_battery_level": "58%", "jump_vehicle_type": "bike"}, {"bike_id": "bike_134690", "name": "44534", "lon": -71.446325, "lat": 41.831455, "is_reserved": 0, "is_disabled": 0, "jump_ebike_battery_level": "63%", "jump_vehicle_type": "bike"}]}}